plotlydash_tornado_cmd/__init__.py
plotlydash_tornado_cmd/main.py
plotlydash_tornado_cmd-0.0.6.dist-info/LICENSE
plotlydash_tornado_cmd-0.0.6.dist-info/METADATA
plotlydash_tornado_cmd-0.0.6.dist-info/WHEEL
plotlydash_tornado_cmd-0.0.6.dist-info/entry_points.txt
plotlydash_tornado_cmd-0.0.6.dist-info/top_level.txt
plotlydash_tornado_cmd-0.0.6.dist-info/RECORD
