Metadata-Version: 2.1
Name: plotlydash-tornado-cmd
Version: 0.0.6
Summary: Command line wrapper to run a named Plotly Dash script inside a Tornado server
Home-page: https://github.com/ideonate/plotlydash-tornado-cmd
Author: Dan Lester
Author-email: dan@ideonate.com
License: UNKNOWN
Platform: UNKNOWN
Classifier: Programming Language :: Python :: 3
Classifier: License :: OSI Approved :: MIT License
Classifier: Operating System :: OS Independent
Requires-Python: >=3.6
Requires-Dist: tornado (>=5.0)
Requires-Dist: Click (>=7.0)
